pyOpenHaptics/__init__.py
pyOpenHaptics/exceptions.py
pyOpenHaptics/hd.py
pyOpenHaptics/hd_callback.py
pyOpenHaptics/hd_define.py
pyOpenHaptics/hd_device.py
pyOpenHaptics/hdu_matrix.py
pyopenhaptics-1.0.1.dist-info/METADATA
pyopenhaptics-1.0.1.dist-info/WHEEL
pyopenhaptics-1.0.1.dist-info/RECORD
