Metadata-Version: 2.3
Name: pyOpenHaptics
Version: 1.0.1
Summary: A minimalist Python wrapper for OpenHaptics
Author-email: Mikel De Iturrate Reyzabal <mikel.de_iturrate_reyzabal@kcl.ac.uk>
License: MIT
Classifier: License :: OSI Approved :: MIT License
Classifier: Operating System :: OS Independent
Classifier: Programming Language :: Python :: 3
Classifier: Programming Language :: Python :: 3.11
Classifier: Programming Language :: Python :: 3.12
Requires-Python: >=3.9
